{"type": "FeatureCollection", "features": [{"type": "Feature", "properties": {"name": "上海站", "address": "上海市静安区秣陵路303号", "tag": "高铁站", "province": "上海", "city": "上海"}, "geometry": {"type": "Point", "coordinates": [121.4510318941668, 31.251558846418007]}}, {"type": "Feature", "properties": {"name": "北京站", "address": "北京市东城区毛家湾胡同甲13号", "tag": "高铁站", "province": "北京", "city": "北京"}, "geometry": {"type": "Point", "coordinates": [116.42084454753214, 39.90201896779932]}}]}
