{"type": "FeatureCollection", "features": [{"type": "Feature", "properties": {"name": "同济大学", "tag": "大学"}, "geometry": {"type": "Point", "coordinates": [121.4974789059845, 31.285413635633574]}}, {"type": "Feature", "properties": {"name": "北京大学", "tag": "大学"}, "geometry": {"type": "Point", "coordinates": [116.30420708125263, 39.991595084258336]}}]}
